{"timestamp": "20131128085242", "nodes": [{"color": "green", "taxid": 893794, "label": "Anabaena variabilis", "strees": [4726], "altlabel": "Anabaena variabilis", "y": 263.6377174292217, "x": 10.297949606143277, "fixed": true, "isleaf": true, "size": 8}, {"color": "green", "taxid": 893795, "label": "Nostoc muscorum", "strees": [4726], "altlabel": "Nostoc muscorum", "y": 216.47859506145426, "x": 741.8329697006241, "fixed": true, "isleaf": true, "size": 8}, {"color": "green", "taxid": 893796, "label": "Nostoc commune", "strees": [4726], "altlabel": "Nostoc commune", "y": 47.646453178319575, "x": 575.874601691849, "fixed": true, "isleaf": true, "size": 8}, {"color": "green", "taxid": 582198, "label": "Cylindrospermum", "strees": [4726], "altlabel": "Cylindrospermum", "y": 260.6910164435542, "x": 740.1068203106779, "fixed": true, "isleaf": false, "size": 8}, {"color": "red", "taxid": 782567, "label": "Nostoc punctiforme", "strees": [], "altlabel": "Nostoc punctiforme", "y": 327.7590982942539, "x": 496.11149254225074, "fixed": true, "isleaf": false, "size": 8}, {"color": "green", "taxid": 724264, "label": "Nodularia spumigena", "strees": [4726], "altlabel": "Nodularia spumigena", "y": 7.344640536831207, "x": 309.59740208456884, "fixed": true, "isleaf": true, "size": 8}, {"color": "green", "taxid": 368778, "label": "Nostocaceae", "strees": [4726], "altlabel": "Nostocaceae", "y": 399.90790608790076, "x": 386.3703305156273, "fixed": true, "isleaf": false, "size": 8}, {"color": "green", "taxid": 368779, "label": "Anabaena", "strees": [4726], "altlabel": "Anabaena", "y": 280.40305199123037, "x": 74.12114060848626, "fixed": true, "isleaf": false, "size": 8}, {"color": "green", "taxid": 566958, "label": "Cylindrospermum stagnale", "strees": [4726], "altlabel": "Cylindrospermum stagnale", "y": 279.89849409859346, "x": 767.9430510211434, "fixed": true, "isleaf": true, "size": 8}, {"color": "green", "taxid": 5163984, "label": "Desmonostoc", "strees": [4726], "altlabel": "Desmonostoc", "y": 200.43842664481804, "x": 713.2976112515414, "fixed": true, "isleaf": false, "size": 8}, {"color": "green", "taxid": 659155, "label": "Nodularia harveyana", "strees": [4726], "altlabel": "Nodularia harveyana", "y": 231.89854142666667, "x": 23.365022860038778, "fixed": true, "isleaf": true, "size": 8}, {"color": "red", "taxid": 578646, "label": "Nodularia", "strees": [], "altlabel": "Nodularia", "y": 416.3690297208491, "x": 209.86996378382392, "fixed": true, "isleaf": false, "size": 8}, {"color": "red", "taxid": 893787, "label": "Nostoc", "strees": [], "altlabel": "Nostoc", "y": 160.5803986234368, "x": 367.06959571696956, "fixed": true, "isleaf": false, "size": 8}, {"color": "blue", "label": "", "strees": [4726], "altlabel": "834506_4017720_Fischerella_musicola", "y": 296.3802880468924, "x": 0.0, "fixed": true, "isleaf": true, "size": 8}, {"color": "blue", "label": "", "strees": [4726], "altlabel": "834589_893787_Nostoc_sp_from_Geosiphon_pryiforme_2", "y": 279.8984940985995, "x": 4.797610010109338, "fixed": true, "isleaf": true, "size": 8}, {"color": "blue", "label": "", "strees": [4726], "altlabel": "", "y": 342.06036054718135, "x": 256.84976507788946, "fixed": true, "isleaf": false, "size": 2}, {"color": "blue", "label": "", "strees": [4726], "altlabel": "", "y": 297.1721314867133, "x": 137.95473367857326, "fixed": true, "isleaf": false, "size": 2}, {"color": "blue", "label": "", "strees": [4726], "altlabel": "834510_893787_Nostoc_sp_PCC7120", "y": 247.62790496169532, "x": 16.49088899852586, "fixed": true, "isleaf": true, "size": 8}, {"color": "blue", "label": "", "strees": [4726], "altlabel": "", "y": 286.06067899107325, "x": 146.58957332117188, "fixed": true, "isleaf": false, "size": 2}, {"color": "blue", "label": "", "strees": [4726], "altlabel": "", "y": 243.45489684054695, "x": 85.06797987313183, "fixed": true, "isleaf": false, "size": 2}, {"color": "blue", "label": "", "strees": [4726], "altlabel": "834514_893787_Nostoc_sp_PCC6720", "y": 216.47859506145946, "x": 30.907691330627927, "fixed": true, "isleaf": true, "size": 8}, {"color": "blue", "label": "", "strees": [4726], "altlabel": "834515_893787_Nostoc_sp_PCC7423", "y": 201.39646426025107, "x": 39.1050033326394, "fixed": true, "isleaf": true, "size": 8}, {"color": "blue", "label": "", "strees": [4726], "altlabel": "", "y": 282.6744021734257, "x": 315.37839725098286, "fixed": true, "isleaf": false, "size": 2}, {"color": "blue", "label": "", "strees": [4726], "altlabel": "834588_893787_Nostoc_sp_from_Peltigera_canina_2", "y": 186.67992527370902, "x": 47.9418621535483, "fixed": true, "isleaf": true, "size": 8}, {"color": "blue", "label": "", "strees": [4726], "altlabel": "", "y": 164.91297947223129, "x": 269.25469254542526, "fixed": true, "isleaf": false, "size": 2}, {"color": "blue", "label": "", "strees": [4726], "altlabel": "834524_893787_Nostoc_sp_from_Peltigera_canina_5", "y": 172.35608105440988, "x": 57.40199324906365, "fixed": true, "isleaf": true, "size": 8}, {"color": "blue", "label": "", "strees": [4726], "altlabel": "834525_893787_Nostoc_sp_from_Peltigera_rufescens_6", "y": 158.45131134224636, "x": 67.46797421540674, "fixed": true, "isleaf": true, "size": 8}, {"color": "blue", "label": "", "strees": [4726], "altlabel": "834526_893787_Nostoc_sp_from_Peltigera_didactyla_4", "y": 144.99122408175174, "x": 78.12126687556389, "fixed": true, "isleaf": true, "size": 8}, {"color": "blue", "label": "", "strees": [4726], "altlabel": "834557_893787_Nostoc_sp_from_Anthoceros_sp_1", "y": 132.00060826081432, "x": 89.34225142041987, "fixed": true, "isleaf": true, "size": 8}, {"color": "blue", "label": "", "strees": [4726], "altlabel": "834558_893787_Nostoc_sp_from_Peltigera_rufescens_7", "y": 119.5033882576356, "x": 101.11026254189824, "fixed": true, "isleaf": true, "size": 8}, {"color": "blue", "label": "", "strees": [4726], "altlabel": "834559_893787_Nostoc_sp_from_Peltigera_didactyla_1", "y": 107.52257978001177, "x": 113.40362749156014, "fixed": true, "isleaf": true, "size": 8}, {"color": "blue", "label": "", "strees": [4726], "altlabel": "834560_893787_Nostoc_sp_from_Peltigera_rufescens_1", "y": 96.08024747808122, "x": 126.19970599457389, "fixed": true, "isleaf": true, "size": 8}, {"color": "blue", "label": "", "strees": [4726], "altlabel": "834561_893787_Nostoc_sp_from_Peltigera_rufescens_2", "y": 85.19746430860607, "x": 139.47493194554224, "fixed": true, "isleaf": true, "size": 8}, {"color": "blue", "label": "", "strees": [4726], "altlabel": "834562_893787_Nostoc_sp_from_Peltigera_rufescens_3", "y": 74.89427272561716, "x": 153.20485680940484, "fixed": true, "isleaf": true, "size": 8}, {"color": "blue", "label": "", "strees": [4726], "altlabel": "834563_893787_Nostoc_sp_from_Peltigera_didactyla_2", "y": 65.18964776890596, "x": 167.36419464747712, "fixed": true, "isleaf": true, "size": 8}, {"color": "blue", "label": "", "strees": [4726], "altlabel": "834564_893787_Nostoc_sp_from_Peltigera_rufescens_4", "y": 56.10146211833364, "x": 181.92686868570985, "fixed": true, "isleaf": true, "size": 8}, {"color": "blue", "label": "", "strees": [4726], "altlabel": "834565_893787_Nostoc_sp_from_Peltigera_canina_4", "y": 47.64645317832105, "x": 196.86605933940305, "fixed": true, "isleaf": true, "size": 8}, {"color": "blue", "label": "", "strees": [4726], "altlabel": "834566_893787_Nostoc_sp_from_Peltigera_neopolydactyla", "y": 39.840192253136195, "x": 212.15425360592846, "fixed": true, "isleaf": true, "size": 8}, {"color": "blue", "label": "", "strees": [4726], "altlabel": "834578_893787_Nostoc_sp_from_Peltigera_canina_3", "y": 32.69705586974976, "x": 227.763295734497, "fixed": true, "isleaf": true, "size": 8}, {"color": "blue", "label": "", "strees": [4726], "altlabel": "834586_893787_Nostoc_sp_from_Peltigera_rufescens_5", "y": 26.23019930107074, "x": 243.66443907965368, "fixed": true, "isleaf": true, "size": 8}, {"color": "blue", "label": "", "strees": [4726], "altlabel": "834587_782567_Nostoc_punctiforme_from_Blasia_pusilla_1", "y": 20.45153233832525, "x": 259.8283990430026, "fixed": true, "isleaf": true, "size": 8}, {"color": "blue", "label": "", "strees": [4726], "altlabel": "", "y": 96.03942188330296, "x": 275.98645164797955, "fixed": true, "isleaf": false, "size": 2}, {"color": "blue", "label": "", "strees": [4726], "altlabel": "834585_893787_Nostoc_sp_from_Peltigera_lepidophora", "y": 15.371697357195728, "x": 276.225407005664, "fixed": true, "isleaf": true, "size": 8}, {"color": "blue", "label": "", "strees": [4726], "altlabel": "", "y": 54.34813517194118, "x": 288.567370330274, "fixed": true, "isleaf": false, "size": 2}, {"color": "blue", "label": "", "strees": [4726], "altlabel": "834584_782567_Nostoc_punctiforme", "y": 11.000049718118419, "x": 292.8252651521313, "fixed": true, "isleaf": true, "size": 8}, {"color": "blue", "label": "", "strees": [4726], "altlabel": "", "y": 27.55037884044765, "x": 305.71776577447207, "fixed": true, "isleaf": false, "size": 2}, {"color": "blue", "label": "", "strees": [4726], "altlabel": "834583_578646_Nodularia_sp_PCC7804", "y": 4.412201856905995, "x": 326.5109291251229, "fixed": true, "isleaf": true, "size": 8}, {"color": "blue", "label": "", "strees": [4726], "altlabel": "", "y": 67.20466267475763, "x": 336.0858982797555, "fixed": true, "isleaf": false, "size": 2}, {"color": "blue", "label": "", "strees": [4726], "altlabel": "834519_893787_Nostoc_sp_from_Peltigera_membranacea_3", "y": 2.2081342515718916, "x": 343.5346972025552, "fixed": true, "isleaf": true, "size": 8}, {"color": "blue", "label": "", "strees": [4726], "altlabel": "834520_893787_Nostoc_sp_from_Peltigera_membranacea_2", "y": 0.7364968776617502, "x": 360.6373542184339, "fixed": true, "isleaf": true, "size": 8}, {"color": "blue", "label": "", "strees": [4726], "altlabel": "834521_893787_Nostoc_sp_from_Peltigera_horizontalis", "y": 5.684341886080802e-14, "x": 377.787402787236, "fixed": true, "isleaf": true, "size": 8}, {"color": "blue", "label": "", "strees": [4726], "altlabel": "834522_893787_Nostoc_sp_from_Peltigera_membranacea_5", "y": 0.0, "x": 394.9532582440163, "fixed": true, "isleaf": true, "size": 8}, {"color": "blue", "label": "", "strees": [4726], "altlabel": "834523_893787_Nostoc_sp_from_Peltigera_aphthosa_1", "y": 0.7364968776615797, "x": 412.10330681281874, "fixed": true, "isleaf": true, "size": 8}, {"color": "blue", "label": "", "strees": [4726], "altlabel": "", "y": 87.1878373539742, "x": 372.95861072025673, "fixed": true, "isleaf": false, "size": 2}, {"color": "blue", "label": "", "strees": [4726], "altlabel": "834568_893787_Nostoc_sp_from_Peltigera_canina_1", "y": 2.208134251571721, "x": 429.20596382869746, "fixed": true, "isleaf": true, "size": 8}, {"color": "blue", "label": "", "strees": [4726], "altlabel": "834569_893787_Nostoc_sp_from_Peltigera_membranacea_1", "y": 4.412201856905654, "x": 446.2297319061295, "fixed": true, "isleaf": true, "size": 8}, {"color": "blue", "label": "", "strees": [4726], "altlabel": "834577_893787_Nostoc_sp_from_Peltigera_aphthosa_2", "y": 7.344640536830809, "x": 463.1432589466839, "fixed": true, "isleaf": true, "size": 8}, {"color": "blue", "label": "", "strees": [4726], "altlabel": "", "y": 51.342227684670036, "x": 465.684657149411, "fixed": true, "isleaf": false, "size": 2}, {"color": "blue", "label": "", "strees": [4726], "altlabel": "834571_893787_Nostoc_sp_from_Sticta_beauvoisii", "y": 11.000049718117964, "x": 479.91539587912143, "fixed": true, "isleaf": true, "size": 8}, {"color": "blue", "label": "", "strees": [4726], "altlabel": "834572_893787_Nostoc_sp_from_Lobaria_amplissima", "y": 15.371697357195103, "x": 496.51525402558843, "fixed": true, "isleaf": true, "size": 8}, {"color": "blue", "label": "", "strees": [4726], "altlabel": "834573_893787_Nostoc_sp_from_Nephroma_bellum", "y": 20.451532338324455, "x": 512.9122619882498, "fixed": true, "isleaf": true, "size": 8}, {"color": "blue", "label": "", "strees": [4726], "altlabel": "834574_893787_Nostoc_sp_from_Nephroma_helveticum", "y": 26.230199301069945, "x": 529.0762219515988, "fixed": true, "isleaf": true, "size": 8}, {"color": "blue", "label": "", "strees": [4726], "altlabel": "834575_893787_Nostoc_sp_from_Pannaria_conoplea", "y": 32.69705586974868, "x": 544.9773652967551, "fixed": true, "isleaf": true, "size": 8}, {"color": "blue", "label": "", "strees": [4726], "altlabel": "834576_893787_Nostoc_sp_from_Sticta_fuliginosa", "y": 39.84019225313506, "x": 560.5864074253238, "fixed": true, "isleaf": true, "size": 8}, {"color": "blue", "label": "", "strees": [4726], "altlabel": "", "y": 146.02078952790043, "x": 410.5278503267019, "fixed": true, "isleaf": false, "size": 2}, {"color": "blue", "label": "", "strees": [4726], "altlabel": "", "y": 115.04931829297158, "x": 491.331000503977, "fixed": true, "isleaf": false, "size": 2}, {"color": "blue", "label": "", "strees": [4726], "altlabel": "834538_893787_Nostoc_sp_from_Stangeria_paradoxa", "y": 56.10146211833188, "x": 590.8137923455419, "fixed": true, "isleaf": true, "size": 8}, {"color": "blue", "label": "", "strees": [4726], "altlabel": "", "y": 107.38257179686417, "x": 550.6850079362496, "fixed": true, "isleaf": false, "size": 2}, {"color": "blue", "label": "", "strees": [4726], "altlabel": "", "y": 87.01131864340715, "x": 585.226955477623, "fixed": true, "isleaf": false, "size": 2}, {"color": "blue", "label": "", "strees": [4726], "altlabel": "834536_893787_Nostoc_sp_from_Leptogium_gelatinosum", "y": 65.18964776890408, "x": 605.3764663837746, "fixed": true, "isleaf": true, "size": 8}, {"color": "blue", "label": "", "strees": [4726], "altlabel": "834537_893787_Nostoc_sp_from_Massalongia_carnosa", "y": 74.89427272561505, "x": 619.5358042218468, "fixed": true, "isleaf": true, "size": 8}, {"color": "blue", "label": "", "strees": [4726], "altlabel": "", "y": 106.30980229756955, "x": 612.4264314252506, "fixed": true, "isleaf": false, "size": 2}, {"color": "blue", "label": "", "strees": [4726], "altlabel": "834531_893787_Nostoc_sp_from_Peltigera_didactyla_5", "y": 85.19746430860357, "x": 633.2657290857092, "fixed": true, "isleaf": true, "size": 8}, {"color": "blue", "label": "", "strees": [4726], "altlabel": "834532_893787_Nostoc_sp_from_Encephalartos_natalensis", "y": 96.0802474780786, "x": 646.5409550366776, "fixed": true, "isleaf": true, "size": 8}, {"color": "blue", "label": "", "strees": [4726], "altlabel": "834533_893787_Nostoc_sp_from_Collema_crispum", "y": 107.52257978000887, "x": 659.3370335396914, "fixed": true, "isleaf": true, "size": 8}, {"color": "blue", "label": "", "strees": [4726], "altlabel": "834534_893787_Nostoc_sp_from_Cycas_circinalis", "y": 119.50338825763248, "x": 671.6303984893533, "fixed": true, "isleaf": true, "size": 8}, {"color": "blue", "label": "", "strees": [4726], "altlabel": "", "y": 156.85759896002475, "x": 552.9069235615176, "fixed": true, "isleaf": false, "size": 2}, {"color": "blue", "label": "", "strees": [4726], "altlabel": "834553_893787_Nostoc_sp_from_Lobaria_hallii", "y": 132.00060826081074, "x": 683.3984096108315, "fixed": true, "isleaf": true, "size": 8}, {"color": "blue", "label": "", "strees": [4726], "altlabel": "834554_893787_Nostoc_sp_from_Peltigera_degeni", "y": 144.99122408174804, "x": 694.6193941556877, "fixed": true, "isleaf": true, "size": 8}, {"color": "blue", "label": "", "strees": [4726], "altlabel": "834555_893787_Nostoc_sp_from_Peltigera_membranacea_4", "y": 158.45131134224226, "x": 705.2726868158447, "fixed": true, "isleaf": true, "size": 8}, {"color": "blue", "label": "", "strees": [4726], "altlabel": "", "y": 168.46349209927627, "x": 630.7090693230165, "fixed": true, "isleaf": false, "size": 2}, {"color": "blue", "label": "", "strees": [4726], "altlabel": "834552_782567_Nostoc_punctiforme_from_Geosiphon_pyriforme_1", "y": 172.35608105440548, "x": 715.3386677821879, "fixed": true, "isleaf": true, "size": 8}, {"color": "blue", "label": "", "strees": [4726], "altlabel": "", "y": 184.3999526051663, "x": 684.7369838174502, "fixed": true, "isleaf": false, "size": 2}, {"color": "blue", "label": "", "strees": [4726], "altlabel": "834549_893787_Nostoc_sp_from_Blasia_pusilla_3", "y": 186.67992527370458, "x": 724.7987988777035, "fixed": true, "isleaf": true, "size": 8}, {"color": "blue", "label": "", "strees": [4726], "altlabel": "834550_893787_Nostoc_sp_from_Peltigera_didactyla_3", "y": 201.39646426024612, "x": 733.6356576986125, "fixed": true, "isleaf": true, "size": 8}, {"color": "blue", "label": "", "strees": [4726], "altlabel": "", "y": 199.57793330774803, "x": 645.2736275116304, "fixed": true, "isleaf": false, "size": 2}, {"color": "blue", "label": "", "strees": [4726], "altlabel": "834541_893787_Nostoc_sp_from_Blasia_pusilla_2", "y": 231.89854142666138, "x": 749.3756381712134, "fixed": true, "isleaf": true, "size": 8}, {"color": "blue", "label": "", "strees": [4726], "altlabel": "", "y": 241.47885565180061, "x": 712.2615611535884, "fixed": true, "isleaf": false, "size": 2}, {"color": "blue", "label": "", "strees": [4726], "altlabel": "834543_893787_Nostoc_sp_from_Anthoceros_sp_2", "y": 247.62790496168958, "x": 756.2497720327265, "fixed": true, "isleaf": true, "size": 8}, {"color": "blue", "label": "", "strees": [4726], "altlabel": "834544_782567_Nostoc_punctiforme_from_Macrozamia_sp", "y": 263.6377174292155, "x": 762.4427114251091, "fixed": true, "isleaf": true, "size": 8}, {"color": "blue", "label": "", "strees": [4726], "altlabel": "834546_782567_Nostoc_punctiforme_from_Gunnera_manicata", "y": 296.38028804688594, "x": 772.7406610312529, "fixed": true, "isleaf": true, "size": 8}], "links": [{"target": 8, "width": 3, "color": "green", "source": 3, "strees": [4726], "taxedge": true}, {"target": 40, "width": 1, "color": "red", "source": 4, "strees": [], "taxedge": true}, {"target": 44, "width": 1, "color": "red", "source": 4, "strees": [], "taxedge": true}, {"target": 81, "width": 1, "color": "red", "source": 4, "strees": [], "taxedge": true}, {"target": 89, "width": 1, "color": "red", "source": 4, "strees": [], "taxedge": true}, {"target": 90, "width": 1, "color": "red", "source": 4, "strees": [], "taxedge": true}, {"target": 3, "width": 1, "color": "red", "source": 6, "strees": [], "taxedge": true}, {"target": 7, "width": 1, "color": "red", "source": 6, "strees": [], "taxedge": true}, {"target": 9, "width": 1, "color": "red", "source": 6, "strees": [], "taxedge": true}, {"target": 11, "width": 1, "color": "red", "source": 6, "strees": [], "taxedge": true}, {"target": 12, "width": 1, "color": "red", "source": 6, "strees": [], "taxedge": true}, {"target": 13, "width": 3, "color": "blue", "source": 6, "strees": [4726], "taxedge": false}, {"target": 14, "width": 3, "color": "blue", "source": 6, "strees": [4726], "taxedge": false}, {"target": 15, "width": 3, "color": "blue", "source": 6, "strees": [4726], "taxedge": false}, {"target": 22, "width": 3, "color": "blue", "source": 6, "strees": [4726], "taxedge": false}, {"target": 0, "width": 3, "color": "green", "source": 7, "strees": [4726], "taxedge": true}, {"target": 1, "width": 3, "color": "green", "source": 9, "strees": [4726], "taxedge": true}, {"target": 5, "width": 1, "color": "red", "source": 11, "strees": [], "taxedge": true}, {"target": 10, "width": 1, "color": "red", "source": 11, "strees": [], "taxedge": true}, {"target": 46, "width": 1, "color": "red", "source": 11, "strees": [], "taxedge": true}, {"target": 2, "width": 1, "color": "red", "source": 12, "strees": [], "taxedge": true}, {"target": 4, "width": 1, "color": "red", "source": 12, "strees": [], "taxedge": true}, {"target": 14, "width": 1, "color": "red", "source": 12, "strees": [], "taxedge": true}, {"target": 17, "width": 1, "color": "red", "source": 12, "strees": [], "taxedge": true}, {"target": 20, "width": 1, "color": "red", "source": 12, "strees": [], "taxedge": true}, {"target": 21, "width": 1, "color": "red", "source": 12, "strees": [], "taxedge": true}, {"target": 23, "width": 1, "color": "red", "source": 12, "strees": [], "taxedge": true}, {"target": 25, "width": 1, "color": "red", "source": 12, "strees": [], "taxedge": true}, {"target": 26, "width": 1, "color": "red", "source": 12, "strees": [], "taxedge": true}, {"target": 27, "width": 1, "color": "red", "source": 12, "strees": [], "taxedge": true}, {"target": 28, "width": 1, "color": "red", "source": 12, "strees": [], "taxedge": true}, {"target": 29, "width": 1, "color": "red", "source": 12, "strees": [], "taxedge": true}, {"target": 30, "width": 1, "color": "red", "source": 12, "strees": [], "taxedge": true}, {"target": 31, "width": 1, "color": "red", "source": 12, "strees": [], "taxedge": true}, {"target": 32, "width": 1, "color": "red", "source": 12, "strees": [], "taxedge": true}, {"target": 33, "width": 1, "color": "red", "source": 12, "strees": [], "taxedge": true}, {"target": 34, "width": 1, "color": "red", "source": 12, "strees": [], "taxedge": true}, {"target": 35, "width": 1, "color": "red", "source": 12, "strees": [], "taxedge": true}, {"target": 36, "width": 1, "color": "red", "source": 12, "strees": [], "taxedge": true}, {"target": 37, "width": 1, "color": "red", "source": 12, "strees": [], "taxedge": true}, {"target": 38, "width": 1, "color": "red", "source": 12, "strees": [], "taxedge": true}, {"target": 39, "width": 1, "color": "red", "source": 12, "strees": [], "taxedge": true}, {"target": 42, "width": 1, "color": "red", "source": 12, "strees": [], "taxedge": true}, {"target": 48, "width": 1, "color": "red", "source": 12, "strees": [], "taxedge": true}, {"target": 49, "width": 1, "color": "red", "source": 12, "strees": [], "taxedge": true}, {"target": 50, "width": 1, "color": "red", "source": 12, "strees": [], "taxedge": true}, {"target": 51, "width": 1, "color": "red", "source": 12, "strees": [], "taxedge": true}, {"target": 52, "width": 1, "color": "red", "source": 12, "strees": [], "taxedge": true}, {"target": 54, "width": 1, "color": "red", "source": 12, "strees": [], "taxedge": true}, {"target": 55, "width": 1, "color": "red", "source": 12, "strees": [], "taxedge": true}, {"target": 56, "width": 1, "color": "red", "source": 12, "strees": [], "taxedge": true}, {"target": 58, "width": 1, "color": "red", "source": 12, "strees": [], "taxedge": true}, {"target": 59, "width": 1, "color": "red", "source": 12, "strees": [], "taxedge": true}, {"target": 60, "width": 1, "color": "red", "source": 12, "strees": [], "taxedge": true}, {"target": 61, "width": 1, "color": "red", "source": 12, "strees": [], "taxedge": true}, {"target": 62, "width": 1, "color": "red", "source": 12, "strees": [], "taxedge": true}, {"target": 63, "width": 1, "color": "red", "source": 12, "strees": [], "taxedge": true}, {"target": 66, "width": 1, "color": "red", "source": 12, "strees": [], "taxedge": true}, {"target": 69, "width": 1, "color": "red", "source": 12, "strees": [], "taxedge": true}, {"target": 70, "width": 1, "color": "red", "source": 12, "strees": [], "taxedge": true}, {"target": 72, "width": 1, "color": "red", "source": 12, "strees": [], "taxedge": true}, {"target": 73, "width": 1, "color": "red", "source": 12, "strees": [], "taxedge": true}, {"target": 74, "width": 1, "color": "red", "source": 12, "strees": [], "taxedge": true}, {"target": 75, "width": 1, "color": "red", "source": 12, "strees": [], "taxedge": true}, {"target": 77, "width": 1, "color": "red", "source": 12, "strees": [], "taxedge": true}, {"target": 78, "width": 1, "color": "red", "source": 12, "strees": [], "taxedge": true}, {"target": 79, "width": 1, "color": "red", "source": 12, "strees": [], "taxedge": true}, {"target": 83, "width": 1, "color": "red", "source": 12, "strees": [], "taxedge": true}, {"target": 84, "width": 1, "color": "red", "source": 12, "strees": [], "taxedge": true}, {"target": 86, "width": 1, "color": "red", "source": 12, "strees": [], "taxedge": true}, {"target": 88, "width": 1, "color": "red", "source": 12, "strees": [], "taxedge": true}, {"target": 16, "width": 3, "color": "blue", "source": 15, "strees": [4726], "taxedge": false}, {"target": 18, "width": 3, "color": "blue", "source": 15, "strees": [4726], "taxedge": false}, {"target": 7, "width": 3, "color": "blue", "source": 16, "strees": [4726], "taxedge": false}, {"target": 17, "width": 3, "color": "blue", "source": 16, "strees": [4726], "taxedge": false}, {"target": 10, "width": 3, "color": "blue", "source": 18, "strees": [4726], "taxedge": false}, {"target": 19, "width": 3, "color": "blue", "source": 18, "strees": [4726], "taxedge": false}, {"target": 20, "width": 3, "color": "blue", "source": 19, "strees": [4726], "taxedge": false}, {"target": 21, "width": 3, "color": "blue", "source": 19, "strees": [4726], "taxedge": false}, {"target": 23, "width": 3, "color": "blue", "source": 22, "strees": [4726], "taxedge": false}, {"target": 24, "width": 3, "color": "blue", "source": 22, "strees": [4726], "taxedge": false}, {"target": 25, "width": 3, "color": "blue", "source": 24, "strees": [4726], "taxedge": false}, {"target": 26, "width": 3, "color": "blue", "source": 24, "strees": [4726], "taxedge": false}, {"target": 27, "width": 3, "color": "blue", "source": 24, "strees": [4726], "taxedge": false}, {"target": 28, "width": 3, "color": "blue", "source": 24, "strees": [4726], "taxedge": false}, {"target": 29, "width": 3, "color": "blue", "source": 24, "strees": [4726], "taxedge": false}, {"target": 30, "width": 3, "color": "blue", "source": 24, "strees": [4726], "taxedge": false}, {"target": 31, "width": 3, "color": "blue", "source": 24, "strees": [4726], "taxedge": false}, {"target": 32, "width": 3, "color": "blue", "source": 24, "strees": [4726], "taxedge": false}, {"target": 33, "width": 3, "color": "blue", "source": 24, "strees": [4726], "taxedge": false}, {"target": 34, "width": 3, "color": "blue", "source": 24, "strees": [4726], "taxedge": false}, {"target": 35, "width": 3, "color": "blue", "source": 24, "strees": [4726], "taxedge": false}, {"target": 36, "width": 3, "color": "blue", "source": 24, "strees": [4726], "taxedge": false}, {"target": 37, "width": 3, "color": "blue", "source": 24, "strees": [4726], "taxedge": false}, {"target": 38, "width": 3, "color": "blue", "source": 24, "strees": [4726], "taxedge": false}, {"target": 39, "width": 3, "color": "blue", "source": 24, "strees": [4726], "taxedge": false}, {"target": 40, "width": 3, "color": "blue", "source": 24, "strees": [4726], "taxedge": false}, {"target": 41, "width": 3, "color": "blue", "source": 24, "strees": [4726], "taxedge": false}, {"target": 47, "width": 3, "color": "blue", "source": 24, "strees": [4726], "taxedge": false}, {"target": 53, "width": 3, "color": "blue", "source": 24, "strees": [4726], "taxedge": false}, {"target": 64, "width": 3, "color": "blue", "source": 24, "strees": [4726], "taxedge": false}, {"target": 42, "width": 3, "color": "blue", "source": 41, "strees": [4726], "taxedge": false}, {"target": 43, "width": 3, "color": "blue", "source": 41, "strees": [4726], "taxedge": false}, {"target": 44, "width": 3, "color": "blue", "source": 43, "strees": [4726], "taxedge": false}, {"target": 45, "width": 3, "color": "blue", "source": 43, "strees": [4726], "taxedge": false}, {"target": 5, "width": 3, "color": "blue", "source": 45, "strees": [4726], "taxedge": false}, {"target": 46, "width": 3, "color": "blue", "source": 45, "strees": [4726], "taxedge": false}, {"target": 48, "width": 3, "color": "blue", "source": 47, "strees": [4726], "taxedge": false}, {"target": 49, "width": 3, "color": "blue", "source": 47, "strees": [4726], "taxedge": false}, {"target": 50, "width": 3, "color": "blue", "source": 47, "strees": [4726], "taxedge": false}, {"target": 51, "width": 3, "color": "blue", "source": 47, "strees": [4726], "taxedge": false}, {"target": 52, "width": 3, "color": "blue", "source": 47, "strees": [4726], "taxedge": false}, {"target": 54, "width": 3, "color": "blue", "source": 53, "strees": [4726], "taxedge": false}, {"target": 55, "width": 3, "color": "blue", "source": 53, "strees": [4726], "taxedge": false}, {"target": 56, "width": 3, "color": "blue", "source": 53, "strees": [4726], "taxedge": false}, {"target": 57, "width": 3, "color": "blue", "source": 53, "strees": [4726], "taxedge": false}, {"target": 58, "width": 3, "color": "blue", "source": 57, "strees": [4726], "taxedge": false}, {"target": 59, "width": 3, "color": "blue", "source": 57, "strees": [4726], "taxedge": false}, {"target": 60, "width": 3, "color": "blue", "source": 57, "strees": [4726], "taxedge": false}, {"target": 61, "width": 3, "color": "blue", "source": 57, "strees": [4726], "taxedge": false}, {"target": 62, "width": 3, "color": "blue", "source": 57, "strees": [4726], "taxedge": false}, {"target": 63, "width": 3, "color": "blue", "source": 57, "strees": [4726], "taxedge": false}, {"target": 2, "width": 3, "color": "blue", "source": 64, "strees": [4726], "taxedge": false}, {"target": 65, "width": 3, "color": "blue", "source": 64, "strees": [4726], "taxedge": false}, {"target": 76, "width": 3, "color": "blue", "source": 64, "strees": [4726], "taxedge": false}, {"target": 66, "width": 3, "color": "blue", "source": 65, "strees": [4726], "taxedge": false}, {"target": 67, "width": 3, "color": "blue", "source": 65, "strees": [4726], "taxedge": false}, {"target": 68, "width": 3, "color": "blue", "source": 67, "strees": [4726], "taxedge": false}, {"target": 71, "width": 3, "color": "blue", "source": 67, "strees": [4726], "taxedge": false}, {"target": 69, "width": 3, "color": "blue", "source": 68, "strees": [4726], "taxedge": false}, {"target": 70, "width": 3, "color": "blue", "source": 68, "strees": [4726], "taxedge": false}, {"target": 72, "width": 3, "color": "blue", "source": 71, "strees": [4726], "taxedge": false}, {"target": 73, "width": 3, "color": "blue", "source": 71, "strees": [4726], "taxedge": false}, {"target": 74, "width": 3, "color": "blue", "source": 71, "strees": [4726], "taxedge": false}, {"target": 75, "width": 3, "color": "blue", "source": 71, "strees": [4726], "taxedge": false}, {"target": 77, "width": 3, "color": "blue", "source": 76, "strees": [4726], "taxedge": false}, {"target": 78, "width": 3, "color": "blue", "source": 76, "strees": [4726], "taxedge": false}, {"target": 79, "width": 3, "color": "blue", "source": 76, "strees": [4726], "taxedge": false}, {"target": 80, "width": 3, "color": "blue", "source": 76, "strees": [4726], "taxedge": false}, {"target": 85, "width": 3, "color": "blue", "source": 76, "strees": [4726], "taxedge": false}, {"target": 81, "width": 3, "color": "blue", "source": 80, "strees": [4726], "taxedge": false}, {"target": 82, "width": 3, "color": "blue", "source": 80, "strees": [4726], "taxedge": false}, {"target": 83, "width": 3, "color": "blue", "source": 82, "strees": [4726], "taxedge": false}, {"target": 84, "width": 3, "color": "blue", "source": 82, "strees": [4726], "taxedge": false}, {"target": 9, "width": 3, "color": "blue", "source": 82, "strees": [4726], "taxedge": false}, {"target": 86, "width": 3, "color": "blue", "source": 85, "strees": [4726], "taxedge": false}, {"target": 87, "width": 3, "color": "blue", "source": 85, "strees": [4726], "taxedge": false}, {"target": 88, "width": 3, "color": "blue", "source": 87, "strees": [4726], "taxedge": false}, {"target": 89, "width": 3, "color": "blue", "source": 87, "strees": [4726], "taxedge": false}, {"target": 3, "width": 3, "color": "blue", "source": 87, "strees": [4726], "taxedge": false}, {"target": 90, "width": 3, "color": "blue", "source": 87, "strees": [4726], "taxedge": false}]}